envattrs/__init__.py
envattrs/converters.py
envattrs-19.1.dist-info/LICENSE
envattrs-19.1.dist-info/METADATA
envattrs-19.1.dist-info/WHEEL
envattrs-19.1.dist-info/top_level.txt
envattrs-19.1.dist-info/RECORD
